django_csrf_view/__init__.py
django_csrf_view/views.py
django_csrf_view-0.1.0.dist-info/LICENSE
django_csrf_view-0.1.0.dist-info/WHEEL
django_csrf_view-0.1.0.dist-info/METADATA
django_csrf_view-0.1.0.dist-info/RECORD
