Metadata-Version: 2.1
Name: django-csrf-view
Version: 0.1.0
Summary: 
Author: Дмитрий
Author-email: acrius@mail.ru
Requires-Python: >=3.5,<4.0
Classifier: Programming Language :: Python :: 3
Classifier: Programming Language :: Python :: 3.5
Classifier: Programming Language :: Python :: 3.6
Classifier: Programming Language :: Python :: 3.7
Requires-Dist: django (>=2.0,<3.0)
